[
	{
	"name": "Early Bird",
	"price": "$70"
	}, {
	"name": "Middle of the Pack",
	"price": "$85"
	}, {
	"name": "Last Call / At The Door",
	"price": "$100"
	}, {
	"name": "Dance Only Pass",
	"price": "$30"
	}, {
	"name": "Lessons Only Pass",
	"price": "$40 / $55 / $70"
	}, {
	"name" : "A La Carte Classes",
	"price" : "$20"
	}, {
	"name" : "A La Carte Evening Dances",
	"price" : "$15"
	}, {
	"name" : "A La Carte Late Night Dance",
	"price" : "$10"
	}, {
	"name" : "Jack and Jill (Lindy or Balboa)",
	"price" : "$5"
	}
]