[
    {
        "day": "Friday Evening (Lindy)",
        "dance": [
            {
                "hours": "7 PM - 8PM",
                "event": "Beginner Lindy Lesson"
            },
            {
                "hours": "8:00 PM - 9:00 PM",
                "event": "TBD"
            },
            {
                "hours": "9:00 PM - 9:50 PM",
                "event": "Michael Gamble and the Rhythm Serenaders"
            },
            {
                "hours": "9:50 PM - 10:10 PM",
                "event": "TBD"
            },
            {
                "hours": "10:10 PM - 11:00 PM",
                "event": "Michael Gamble and the Rhythm Serenaders"
            },
            {
                "hours": "11:00 PM - 11:20 PM",
                "event": "TBD"
            },
            {
                "hours": "11:20 PM - 12:00 AM",
                "event": "Michael Gamble and the Rhythm Serenaders"
            }
        ],
        "danceLocation": "Carlton Commons"
    },
    {
        "day": "Saturday Evening (Balboa)",
        "dance": [
            {
                "hours": "8:00 PM - 9:00 PM",
                "event": "TBD"
            },
            {
                "hours": "9:00 PM - 9:50 PM",
                "event": "Michael Gamble and the Rhythm Serenaders"
            },
            {
                "hours": "9:50 PM - 10:10 PM",
                "event": "TBD"
            },
            {
                "hours": "10:10 PM - 11:00 PM",
                "event": "Michael Gamble and the Rhythm Serenaders"
            },
            {
                "hours": "11:00 PM - 11:20 PM",
                "event": "TBD"
            },
            {
                "hours": "11:20 PM - 12:00 AM",
                "event": "Michael Gamble and the Rhythm Serenaders"
            }
        ],
        "danceLocation": "Carlton Commons"
    },
    {
        "day": "Saturday Late Night - Blues",
        "dance": [
            {
                "hours": "12:30 AM - 1:30 AM",
                "event": "TBD"
            },
            {
                "hours": "1:30 AM - 2:30 AM",
                "event": "TBD"
            },
            {
                "hours": "2:30 AM - 3:30 AM",
                "event": "TBD"
            }
        ],
        "danceLocation": "Carlton Commons"
    },
    {
        "day": "Saturday Late Night - Lindy",
        "dance": [
            {
                "hours": "12:30 AM - 1:30 AM",
                "event": "TBD"
            },
            {
                "hours": "1:30 AM - 3:30",
                "event": "TBD"
            }
        ],
        "danceLocation": "Carlton Commons - Rough Rider Room"
    }
]